d8s_networking/__init__.py
d8s_networking/networking.py
d8s_networking/networking_temp_utils.py
tests/__init__.py
tests/test_networking.py
d8s_networking-0.4.2.dist-info/COPYING
d8s_networking-0.4.2.dist-info/COPYING.LESSER
d8s_networking-0.4.2.dist-info/METADATA
d8s_networking-0.4.2.dist-info/WHEEL
d8s_networking-0.4.2.dist-info/top_level.txt
d8s_networking-0.4.2.dist-info/zip-safe
d8s_networking-0.4.2.dist-info/RECORD
