Metadata-Version: 2.1
Name: d8s-networking
Version: 0.4.2
Summary: Democritus functions for working with network requests.
Home-page: https://github.com/democritus-project/d8s-networking
Author: Floyd Hightower
Author-email: floyd.hightower27@gmail.com
License: GNU Lesser General Public License v3
Keywords: democritus,utility,python,network-requests,network-requests-utility,python-requests
Platform: UNKNOWN
Classifier: Development Status :: 2 - Pre-Alpha
Classifier: Intended Audience :: Developers
Classifier: License :: OSI Approved :: GNU Lesser General Public License v3 or later (LGPLv3+)
Classifier: Natural Language :: English
Classifier: Programming Language :: Python :: 3
Classifier: Programming Language :: Python :: 3.4
Classifier: Programming Language :: Python :: 3.5
Classifier: Programming Language :: Python :: 3.6
Classifier: Programming Language :: Python :: 3.7
Classifier: Programming Language :: Python :: 3.8
Classifier: Programming Language :: Python :: 3.9
Requires-Dist: d8s-hashes (==0.*)
Requires-Dist: d8s-json (==0.*)
Requires-Dist: d8s-user-agents (==0.*)
Requires-Dist: requests
Requires-Dist: importlib-metadata ; python_version < "3.8"
